AUTHORS
CHANGELOG.txt
DESCRIPTION
LICENSE
MANIFEST.in
README.rst
setup.py
django_ga_mail.egg-info/PKG-INFO
django_ga_mail.egg-info/SOURCES.txt
django_ga_mail.egg-info/dependency_links.txt
django_ga_mail.egg-info/requires.txt
django_ga_mail.egg-info/top_level.txt
ga_mail/__init__.py
ga_mail/models.py
ga_mail/tests.py
ga_mail/utils.py
ga_mail/management/__init__.py
ga_mail/management/commands/__init__.py
ga_mail/management/commands/ga_mail.py
ga_mail/templates/ga_mail/block_list.html
ga_mail/templates/ga_mail/block_list.txt
ga_mail/templates/ga_mail/block_value.html
ga_mail/templates/ga_mail/block_value.txt
ga_mail/templates/ga_mail/footer.html
ga_mail/templates/ga_mail/footer.txt
ga_mail/templates/ga_mail/header.html
ga_mail/templates/ga_mail/header.txt