Metadata-Version: 1.0
Name: django-ga-mail
Version: 0.2
Summary: A reusable Django app that sends google analytics report by email.
